<?xml version="1.0" encoding="iso-8859-1"?>
<phonebooks>
  <phonebook>
    <contact><category>0</category><person><realName>Andreas  Hofer</realName></person><telephony nid="2"><number type="mobile" prio="0" id="0">+49 2222 333333</number><number type="work" prio="0" id="1">+49 33333 44444</number></telephony><services/><setup/><modtime>1580385206</modtime><uniqueid>1</uniqueid></contact>
    <contact><category>0</category><person><realName>Asterix  </realName></person><telephony nid="1"><number type="home" prio="0" id="0">+49 111222</number></telephony><services/><setup/><modtime>1580385206</modtime><uniqueid>2</uniqueid></contact>
    <contact><category>0</category><person><realName>Charles de Gaulle</realName></person><telephony nid="1"><number type="home" prio="0" id="0">+49 4455667788</number></telephony><services nid="1"><email classifier="private" id="0">charles@gaulle.fr</email></services><setup/><modtime>1580385206</modtime><uniqueid>3</uniqueid></contact>
    <contact><category>0</category><person><realName>Moritz Max Kunz</realName></person><telephony nid="1"><number type="home" prio="0" id="0">+49133456</number></telephony><services/><setup/><modtime>1580385206</modtime><uniqueid>4</uniqueid></contact>
    <contact><category>0</category><person><realName>Freddie  Mercury</realName></person><telephony nid="1"><number type="home" prio="0" id="0">+49 123456</number></telephony><services/><setup/><modtime>1580385206</modtime><uniqueid>5</uniqueid></contact>
    <contact><category>0</category><person><realName>Johann Wolfgang Goethe</realName></person><telephony nid="2"><number type="home" prio="0" id="0">+49 621 3566666</number><number type="mobile" prio="0" id="1">+49 171 3655555</number></telephony><services nid="1"><email classifier="private" id="0">wolfgang@goethe.de</email></services><setup/><modtime>1580385206</modtime><uniqueid>6</uniqueid></contact>
    <contact><category>0</category><person><realName>Georg Friedrich Händel</realName></person><telephony nid="1"><number type="home" prio="0" id="0">+49 11235</number></telephony><services/><setup/><modtime>1580385206</modtime><uniqueid>7</uniqueid></contact>
    <contact><category>0</category><person><realName>Johannes  Bückler</realName></person><telephony nid="1"><number type="home" prio="0" id="0">+49 01234 5678</number></telephony><services/><setup/><modtime>1580385206</modtime><uniqueid>8</uniqueid></contact>
    <contact><category>0</category><person><realName>Karl  Napf</realName></person><telephony nid="1"><number type="home" prio="0" id="0">+49 1234 56789</number></telephony><services/><setup/><modtime>1580385206</modtime><uniqueid>9</uniqueid></contact>
    <contact><category>0</category><person><realName>Karl  Valentin</realName></person><telephony nid="1"><number type="home" prio="0" id="0">+49 9876 54321</number></telephony><services/><setup/><modtime>1580385206</modtime><uniqueid>10</uniqueid></contact>
    <contact><category>0</category><person><realName>Liese  Meitner</realName></person><telephony nid="1"><number type="home" prio="0" id="0">+49 1234 56789</number></telephony><services/><setup/><modtime>1580385206</modtime><uniqueid>11</uniqueid></contact>
    <contact><category>0</category><person><realName>Max und Moritz</realName></person><telephony nid="1"><number type="home" prio="0" id="0">+49</number></telephony><services/><setup/><modtime>1580385206</modtime><uniqueid>12</uniqueid></contact>
    <contact><category>0</category><person><realName>Pumuckel  </realName></person><telephony nid="1"><number type="home" prio="0" id="0">+49 1111 22222</number></telephony><services/><setup/><modtime>1580385206</modtime><uniqueid>13</uniqueid></contact>
    <contact><category>0</category><person><realName>Salvatore  Dali</realName></person><telephony nid="1"><number type="home" prio="0" id="0">+49</number></telephony><services/><setup/><modtime>1580385206</modtime><uniqueid>14</uniqueid></contact>
    <contact><category>0</category><person><realName>George  Washington</realName></person><telephony nid="1"><number type="home" prio="0" id="0">+49</number></telephony><services/><setup/><modtime>1580385206</modtime><uniqueid>15</uniqueid></contact>
    <contact><category>0</category><person><realName>Wilhelm  Busch</realName></person><telephony nid="1"><number type="home" prio="0" id="0">+49</number></telephony><services/><setup/><modtime>1580385206</modtime><uniqueid>16</uniqueid></contact>
    <contact><category>0</category><person><realName>Wilhelm  Tell</realName></person><telephony nid="1"><number type="home" prio="0" id="0">+49</number></telephony><services/><setup/><modtime>1580385206</modtime><uniqueid>17</uniqueid></contact>
  </phonebook>
</phonebooks>